pympress/__init__.py
pympress/__main__.py
pympress/app.py
pympress/builder.py
pympress/config.py
pympress/deck.py
pympress/dialog.py
pympress/document.py
pympress/editable_label.py
pympress/extras.py
pympress/pointer.py
pympress/scribble.py
pympress/surfacecache.py
pympress/talk_time.py
pympress/ui.py
pympress/util.py
pympress/media_overlays/__init__.py
pympress/media_overlays/base.py
pympress/media_overlays/gif_backend.py
pympress/media_overlays/gst_backend.py
pympress/media_overlays/vlc_backend.py
pympress/share/defaults.conf
pympress/share/css/default.css
pympress/share/locale/cs/LC_MESSAGES/pympress.mo
pympress/share/locale/de/LC_MESSAGES/pympress.mo
pympress/share/locale/es/LC_MESSAGES/pympress.mo
pympress/share/locale/fr/LC_MESSAGES/pympress.mo
pympress/share/locale/hi/LC_MESSAGES/pympress.mo
pympress/share/locale/it/LC_MESSAGES/pympress.mo
pympress/share/locale/ja/LC_MESSAGES/pympress.mo
pympress/share/locale/pl/LC_MESSAGES/pympress.mo
pympress/share/locale/zh_CN/LC_MESSAGES/pympress.mo
pympress/share/locale/zh_HANT/LC_MESSAGES/pympress.mo
pympress/share/locale/zh_TW/LC_MESSAGES/pympress.mo
pympress/share/pixmaps/eraser.png
pympress/share/pixmaps/marker_1.png
pympress/share/pixmaps/marker_2.png
pympress/share/pixmaps/marker_3.png
pympress/share/pixmaps/marker_fill_1.png
pympress/share/pixmaps/marker_fill_2.png
pympress/share/pixmaps/marker_fill_3.png
pympress/share/pixmaps/pointer_blue.png
pympress/share/pixmaps/pointer_green.png
pympress/share/pixmaps/pointer_red.png
pympress/share/pixmaps/pympress-16.png
pympress/share/pixmaps/pympress-22.png
pympress/share/pixmaps/pympress-24.png
pympress/share/pixmaps/pympress-32.png
pympress/share/pixmaps/pympress-48.png
pympress/share/pixmaps/pympress-64.png
pympress/share/pixmaps/pympress.png
pympress/share/xml/autoplay.glade
pympress/share/xml/content.glade
pympress/share/xml/deck.glade
pympress/share/xml/highlight.glade
pympress/share/xml/layout_dialog.glade
pympress/share/xml/media_overlay.glade
pympress-1.8.6.dist-info/licenses/LICENSE.txt
pympress-1.8.6.dist-info/METADATA
pympress-1.8.6.dist-info/WHEEL
pympress-1.8.6.dist-info/entry_points.txt
pympress-1.8.6.dist-info/top_level.txt
pympress-1.8.6.dist-info/RECORD
