Metadata-Version: 2.4
Name: pympress
Version: 1.8.6
Summary: A simple and powerful dual-screen PDF reader designed for presentations
Home-page: https://github.com/Cimbali/pympress/
Download-URL: https://github.com/Cimbali/pympress/releases/latest
Author: Cimbali, Thomas Jost, Christof Rath, Epithumia
Author-email: me@cimba.li
License: GPL-2.0-or-later
Project-URL: Issues, https://github.com/Cimbali/pympress/issues/
Project-URL: Documentation, https://pympress.github.io/
Project-URL: Source Code, https://github.com/Cimbali/pympress/
Keywords: pdf-viewer,beamer,presenter,slide,projector,pdf-reader,presentation,python,poppler,gtk,pygi,vlc
Classifier: Development Status :: 5 - Production/Stable
Classifier: Environment :: X11 Applications :: GTK
Classifier: Intended Audience :: Education
Classifier: Intended Audience :: End Users/Desktop
Classifier: Intended Audience :: Information Technology
Classifier: Intended Audience :: Science/Research
Classifier: Natural Language :: English
Classifier: Natural Language :: French
Classifier: Natural Language :: German
Classifier: Natural Language :: Italian
Classifier: Natural Language :: Polish
Classifier: Natural Language :: Spanish
Classifier: Natural Language :: Czech
Classifier: Natural Language :: Chinese (Simplified)
Classifier: Natural Language :: Chinese (Traditional)
Classifier: Operating System :: OS Independent
Classifier: Programming Language :: Python
Classifier: Topic :: Multimedia :: Graphics :: Presentation
Classifier: Topic :: Multimedia :: Graphics :: Viewers
Requires-Python: >=3.4
License-File: LICENSE.txt
Requires-Dist: watchdog
Requires-Dist: importlib_resources>=1.3; python_version < "3.9"
Provides-Extra: build-sphinx
Requires-Dist: Sphinx; extra == "build-sphinx"
Requires-Dist: myst-parser; extra == "build-sphinx"
Requires-Dist: sphinxcontrib-napoleon; extra == "build-sphinx"
Requires-Dist: sphinx-rtd-theme; extra == "build-sphinx"
Provides-Extra: babel
Requires-Dist: babel; extra == "babel"
Requires-Dist: babelgladeextractor; extra == "babel"
Requires-Dist: setuptools; extra == "babel"
Provides-Extra: vlc-video
Requires-Dist: python-vlc; extra == "vlc-video"
Dynamic: description
Dynamic: download-url
Dynamic: license-file
